geoproject510/__init__.py
geoproject510/common.py
geoproject510/geoproject510.py
tests/__init__.py
tests/test_geoproject510.py
geoproject510-0.0.14.dist-info/LICENSE
geoproject510-0.0.14.dist-info/METADATA
geoproject510-0.0.14.dist-info/WHEEL
geoproject510-0.0.14.dist-info/top_level.txt
geoproject510-0.0.14.dist-info/RECORD
