Metadata-Version: 2.2
Name: geoproject510
Version: 0.0.14
Summary: A package for Geog 510
Author: Casey Shea
Author-email: shea96@gmail.com
Classifier: Programming Language :: Python :: 3
Classifier: License :: OSI Approved :: MIT License
Classifier: Operating System :: OS Independent
License-File: LICENSE
Dynamic: author
Dynamic: author-email
Dynamic: classifier
Dynamic: summary
